{
  "appgroup_id": "6a293d8a132c147c62ca79f1",
  "appgroup_name": "Ferienwohnungsverwaltung",
  "apps": {
    "ferienwohnungen": {
      "app_id": "6a293d78523cacb6cdbf4f0d",
      "name": "Ferienwohnungen",
      "main": false,
      "controls": {
        "bezeichnung": {
          "identifier": "bezeichnung",
          "label": "Bezeichnung",
          "type": "string",
          "subtype": "text",
          "fulltype": "string/text",
          "description": "A string value not longer than 4000 characters (or `null`/`None`).",
          "required": null,
          "in_list": true,
          "in_mobile_list": true,
          "in_text": true,
          "in_structured_search": false,
          "in_fulltext_search": true,
          "in_expert_search": true
        },
        "beschreibung": {
          "identifier": "beschreibung",
          "label": "Beschreibung",
          "type": "string",
          "subtype": "textarea",
          "fulltype": "string/textarea",
          "description": "A string value that can contain multiple lines of text (or `null`/`None`).",
          "required": null,
          "in_list": true,
          "in_mobile_list": true,
          "in_text": false,
          "in_structured_search": false,
          "in_fulltext_search": true,
          "in_expert_search": true
        },
        "max_personen": {
          "identifier": "max_personen",
          "label": "Maximale Personenanzahl",
          "type": "number",
          "subtype": null,
          "fulltype": "number",
          "description": "A decimal number value (or `null`/`None`).",
          "required": null,
          "in_list": true,
          "in_mobile_list": false,
          "in_text": true,
          "in_structured_search": false,
          "in_fulltext_search": true,
          "in_expert_search": true,
          "precision": null
        },
        "lage": {
          "identifier": "lage",
          "label": "Lage / Adresse",
          "type": "string",
          "subtype": "text",
          "fulltype": "string/text",
          "description": "A string value not longer than 4000 characters (or `null`/`None`).",
          "required": null,
          "in_list": true,
          "in_mobile_list": false,
          "in_text": false,
          "in_structured_search": false,
          "in_fulltext_search": true,
          "in_expert_search": true
        },
        "hinweise": {
          "identifier": "hinweise",
          "label": "Besondere Hinweise",
          "type": "string",
          "subtype": "textarea",
          "fulltype": "string/textarea",
          "description": "A string value that can contain multiple lines of text (or `null`/`None`).",
          "required": null,
          "in_list": true,
          "in_mobile_list": false,
          "in_text": false,
          "in_structured_search": false,
          "in_fulltext_search": true,
          "in_expert_search": true
        }
      }
    },
    "buchungen": {
      "app_id": "6a293d7b075920351b0a17fc",
      "name": "Buchungen",
      "main": false,
      "controls": {
        "ferienwohnung": {
          "identifier": "ferienwohnung",
          "label": "Ferienwohnung",
          "type": "applookup",
          "subtype": "select",
          "fulltype": "applookup/select",
          "description": "A reference to a LivingApp record from the target lookup app 'Ferienwohnungen' with the id `6a293d78523cacb6cdbf4f0d` (or `null`/`None`).\n\nThe field value will be a valid record URL in the form `https://my.living-apps.de/rest/apps/6a293d78523cacb6cdbf4f0d/records/<record-id>` (or `null`/`None`).\n\nDisplayed as single-select field in HTML pages.",
          "required": null,
          "in_list": true,
          "in_mobile_list": true,
          "in_text": true,
          "in_structured_search": false,
          "in_fulltext_search": true,
          "in_expert_search": true,
          "lookup_app": "https://my.living-apps.de/rest/apps/6a293d78523cacb6cdbf4f0d"
        },
        "anreise": {
          "identifier": "anreise",
          "label": "Anreisedatum",
          "type": "date",
          "subtype": "date",
          "fulltype": "date/date",
          "description": "A calendar date consisting of year, month and day (or `null`/`None`)\n\nThe field value will be a string in the format `<YYYY>-<MM>-<DD>` (or `null`/`None`).\n\nFor example: `2000-02-29`.\n\nFor `POST`/`PUT`/`PATCH` requests the REST API uses a liberal parsing approach so that strings like `2026`, `February 29, 2000 12:34 MEST`, `letztes Jahr` etc. will be accepted as value date values. However this runs the risk of parsing ambiguous values incorrectly. To ensure reliable parsing it is best to use the canonical format specified above.",
          "required": null,
          "in_list": true,
          "in_mobile_list": true,
          "in_text": true,
          "in_structured_search": false,
          "in_fulltext_search": true,
          "in_expert_search": true
        },
        "abreise": {
          "identifier": "abreise",
          "label": "Abreisedatum",
          "type": "date",
          "subtype": "date",
          "fulltype": "date/date",
          "description": "A calendar date consisting of year, month and day (or `null`/`None`)\n\nThe field value will be a string in the format `<YYYY>-<MM>-<DD>` (or `null`/`None`).\n\nFor example: `2000-02-29`.\n\nFor `POST`/`PUT`/`PATCH` requests the REST API uses a liberal parsing approach so that strings like `2026`, `February 29, 2000 12:34 MEST`, `letztes Jahr` etc. will be accepted as value date values. However this runs the risk of parsing ambiguous values incorrectly. To ensure reliable parsing it is best to use the canonical format specified above.",
          "required": null,
          "in_list": true,
          "in_mobile_list": false,
          "in_text": false,
          "in_structured_search": false,
          "in_fulltext_search": true,
          "in_expert_search": true
        },
        "gast_vorname": {
          "identifier": "gast_vorname",
          "label": "Vorname des Gastes",
          "type": "string",
          "subtype": "text",
          "fulltype": "string/text",
          "description": "A string value not longer than 4000 characters (or `null`/`None`).",
          "required": null,
          "in_list": true,
          "in_mobile_list": false,
          "in_text": false,
          "in_structured_search": false,
          "in_fulltext_search": true,
          "in_expert_search": true
        },
        "gast_nachname": {
          "identifier": "gast_nachname",
          "label": "Nachname des Gastes",
          "type": "string",
          "subtype": "text",
          "fulltype": "string/text",
          "description": "A string value not longer than 4000 characters (or `null`/`None`).",
          "required": null,
          "in_list": true,
          "in_mobile_list": false,
          "in_text": false,
          "in_structured_search": false,
          "in_fulltext_search": true,
          "in_expert_search": true
        },
        "gast_email": {
          "identifier": "gast_email",
          "label": "E-Mail-Adresse",
          "type": "string",
          "subtype": "email",
          "fulltype": "string/email",
          "description": "A valid email address (or `null`/`None`).",
          "required": null,
          "in_list": false,
          "in_mobile_list": false,
          "in_text": false,
          "in_structured_search": false,
          "in_fulltext_search": null,
          "in_expert_search": true
        },
        "gast_telefon": {
          "identifier": "gast_telefon",
          "label": "Telefonnummer",
          "type": "string",
          "subtype": "tel",
          "fulltype": "string/tel",
          "description": "A valid telephone number (or `null`/`None`). Might include country prefix and should include area code.",
          "required": null,
          "in_list": false,
          "in_mobile_list": false,
          "in_text": false,
          "in_structured_search": false,
          "in_fulltext_search": null,
          "in_expert_search": true
        },
        "anzahl_personen": {
          "identifier": "anzahl_personen",
          "label": "Anzahl der Personen",
          "type": "number",
          "subtype": null,
          "fulltype": "number",
          "description": "A decimal number value (or `null`/`None`).",
          "required": null,
          "in_list": false,
          "in_mobile_list": false,
          "in_text": false,
          "in_structured_search": false,
          "in_fulltext_search": null,
          "in_expert_search": true,
          "precision": null
        },
        "bemerkungen": {
          "identifier": "bemerkungen",
          "label": "Bemerkungen",
          "type": "string",
          "subtype": "textarea",
          "fulltype": "string/textarea",
          "description": "A string value that can contain multiple lines of text (or `null`/`None`).",
          "required": null,
          "in_list": false,
          "in_mobile_list": false,
          "in_text": false,
          "in_structured_search": false,
          "in_fulltext_search": null,
          "in_expert_search": true
        }
      }
    }
  },
  "metadata": {
    "apps_list": [
      "Ferienwohnungen",
      "Buchungen"
    ]
  }
}